wagtailhumanitarianicons/__init__.py
wagtailhumanitarianicons/admin.py
wagtailhumanitarianicons/apps.py
wagtailhumanitarianicons/icons.json
wagtailhumanitarianicons/models.py
wagtailhumanitarianicons/tests.py
wagtailhumanitarianicons/utils.py
wagtailhumanitarianicons/views.py
wagtailhumanitarianicons/wagtail_hooks.py
wagtailhumanitarianicons/migrations/__init__.py
wagtailhumanitarianicons/templates/wagtailhumanitarianicons/icons/abduction-kidnapping.svg
wagtailhumanitarianicons/templates/wagtailhumanitarianicons/icons/about.svg
wagtailhumanitarianicons/templates/wagtailhumanitarianicons/icons/add-document.svg
wagtailhumanitarianicons/templates/wagtailhumanitarianicons/icons/add.svg
wagtailhumanitarianicons/templates/wagtailhumanitarianicons/icons/advocacy.svg
wagtailhumanitarianicons/templates/wagtailhumanitarianicons/icons/affected-population.svg
wagtailhumanitarianicons/templates/wagtailhumanitarianicons/icons/agile.svg
wagtailhumanitarianicons/templates/wagtailhumanitarianicons/icons/agriculture.svg
wagtailhumanitarianicons/templates/wagtailhumanitarianicons/icons/airport-affected.svg
wagtailhumanitarianicons/templates/wagtailhumanitarianicons/icons/airport-closed.svg
wagtailhumanitarianicons/templates/wagtailhumanitarianicons/icons/airport-destroyed.svg
wagtailhumanitarianicons/templates/wagtailhumanitarianicons/icons/airport-military.svg
wagtailhumanitarianicons/templates/wagtailhumanitarianicons/icons/airport-not-affected.svg
wagtailhumanitarianicons/templates/wagtailhumanitarianicons/icons/airport.svg
wagtailhumanitarianicons/templates/wagtailhumanitarianicons/icons/alert.svg
wagtailhumanitarianicons/templates/wagtailhumanitarianicons/icons/analysis.svg
wagtailhumanitarianicons/templates/wagtailhumanitarianicons/icons/apps.svg
wagtailhumanitarianicons/templates/wagtailhumanitarianicons/icons/arrest-detention.svg
wagtailhumanitarianicons/templates/wagtailhumanitarianicons/icons/assault.svg
wagtail_humanitarian_icons-2.0.0.dist-info/METADATA
wagtail_humanitarian_icons-2.0.0.dist-info/WHEEL
wagtail_humanitarian_icons-2.0.0.dist-info/top_level.txt
wagtail_humanitarian_icons-2.0.0.dist-info/RECORD
