Metadata-Version: 2.1
Name: wagtail-humanitarian-icons
Version: 2.0.0
Summary: Ocha Humanitarian Icons, for use in  Wagtail projects, with an icon chooser widget.
Home-page: https://github.com/wmo-raf/wagtail-humanitarian-icons
Author: Erick Otenyo
Author-email: otenyo.erick@gmail.com
License: MIT
Classifier: Development Status :: 5 - Production/Stable
Classifier: Environment :: Web Environment
Classifier: Intended Audience :: Developers
Classifier: License :: OSI Approved :: MIT License
Classifier: Operating System :: OS Independent
Classifier: Programming Language :: Python :: 3 :: Only
Classifier: Programming Language :: Python :: 3.9
Classifier: Programming Language :: Python :: Implementation :: CPython
Classifier: Topic :: Software Development :: Libraries :: Application Frameworks
Classifier: Topic :: Software Development :: Libraries :: Python Modules
Requires-Python: >=3.9
Requires-Dist: wagtail (>=4.2.2)
